{
  "configs": [
    "accounts13.xml",
    "globalelement.xml"
  ],
  "secureProperties": [],
  "redeploymentEnabled": true,
  "name": "com.mycompany:accounts13:1.0.0-SNAPSHOT",
  "minMuleVersion": "4.3.0",
  "requiredProduct": "MULE",
  "classLoaderModelLoaderDescriptor": {
    "id": "mule",
    "attributes": {
      "exportedPackages": [],
      "exportedResources": [
        "accounts13.xml",
        "globalelement.xml",
        "log4j2.xml"
      ]
    }
  },
  "bundleDescriptorLoader": {
    "id": "mule",
    "attributes": {}
  }
}